fbdiff.py
fbdiff-0.8.6.dist-info/LICENSE
fbdiff-0.8.6.dist-info/METADATA
fbdiff-0.8.6.dist-info/WHEEL
fbdiff-0.8.6.dist-info/entry_points.txt
fbdiff-0.8.6.dist-info/top_level.txt
fbdiff-0.8.6.dist-info/RECORD
