Metadata-Version: 2.1
Name: fbdiff
Version: 0.8.6
Summary: Show a summary of table differences between two OpenType fonts.
Home-page: http://github.com/justvanrossum/fbdiff
Author: Just van Rossum
Author-email: justvanrossum@gmail.com
License: Apache License 2.0
Platform: Any
Classifier: Development Status :: 4 - Beta
Classifier: Environment :: Console
Classifier: Environment :: Other Environment
Classifier: Intended Audience :: Developers
Classifier: Intended Audience :: End Users/Desktop
Classifier: License :: OSI Approved :: Apache Software License
Classifier: Natural Language :: English
Classifier: Operating System :: OS Independent
Classifier: Programming Language :: Python
Classifier: Programming Language :: Python :: 3
Classifier: Topic :: Text Processing :: Fonts
Requires-Python: >=3.7
Requires-Dist: fonttools
